serialalchemy/__init__.py
serialalchemy-0.5.6.dist-info/METADATA
serialalchemy-0.5.6.dist-info/WHEEL
serialalchemy-0.5.6.dist-info/RECORD
