Metadata-Version: 2.4
Name: SerialAlchemy
Version: 0.5.6
Summary: Mixin for serializing SQLAlchemy ORM classes into dict or json
Author-email: Matt Schmidt <matt@digitaleye.com>
Requires-Python: >=3.11
Requires-Dist: python-dateutil>=2.9.0.post0
Requires-Dist: pytz>=2025.2
Requires-Dist: sqlalchemy>=2.0.41
